LICENSE
MANIFEST.in
README.md
requirements.txt
setup.py
webarticle2text/__init__.py
webarticle2text/tests.py
webarticle2text/webarticle2text.py
webarticle2text.egg-info/PKG-INFO
webarticle2text.egg-info/SOURCES.txt
webarticle2text.egg-info/dependency_links.txt
webarticle2text.egg-info/requires.txt
webarticle2text.egg-info/top_level.txt
webarticle2text/fixtures/SAMPLE1.html
webarticle2text/fixtures/compare/.gitignore
webarticle2text/fixtures/compare/page1.beautifulsoup_html5lib.actual.txt
webarticle2text/fixtures/compare/page1.beautifulsoup_lxml.actual.txt
webarticle2text/fixtures/compare/page1.expected.txt
webarticle2text/fixtures/compare/page1.goose.actual.txt
webarticle2text/fixtures/compare/page1.html
webarticle2text/fixtures/compare/page1.html2text.actual.txt
webarticle2text/fixtures/compare/page1.newspaper.actual.txt
webarticle2text/fixtures/compare/page1.readability.actual.txt
webarticle2text/fixtures/compare/page1.webarticle2text.actual.txt
webarticle2text/fixtures/compare/page2.beautifulsoup_html5lib.actual.txt
webarticle2text/fixtures/compare/page2.beautifulsoup_lxml.actual.txt
webarticle2text/fixtures/compare/page2.expected.txt
webarticle2text/fixtures/compare/page2.goose.actual.txt
webarticle2text/fixtures/compare/page2.html
webarticle2text/fixtures/compare/page2.html2text.actual.txt
webarticle2text/fixtures/compare/page2.newspaper.actual.txt
webarticle2text/fixtures/compare/page2.readability.actual.txt
webarticle2text/fixtures/compare/page2.webarticle2text.actual.txt
webarticle2text/fixtures/compare/page3.beautifulsoup_html5lib.actual.txt
webarticle2text/fixtures/compare/page3.beautifulsoup_lxml.actual.txt
webarticle2text/fixtures/compare/page3.expected.txt
webarticle2text/fixtures/compare/page3.goose.actual.txt
webarticle2text/fixtures/compare/page3.html
webarticle2text/fixtures/compare/page3.html2text.actual.txt
webarticle2text/fixtures/compare/page3.newspaper.actual.txt
webarticle2text/fixtures/compare/page3.readability.actual.txt
webarticle2text/fixtures/compare/page3.webarticle2text.actual.txt
webarticle2text/fixtures/compare/page4.beautifulsoup_html5lib.actual.txt
webarticle2text/fixtures/compare/page4.beautifulsoup_lxml.actual.txt
