Metadata-Version: 1.1
Name: webarticle2text
Version: 3.0.2
Summary: Extracts the main article text from a webpage.
Home-page: https://github.com/chrisspen/webarticle2text
Author: Chris Spencer
Author-email: chrisspen@gmail.com
License: LGPL License
Platform: OS Independent
Classifier: Programming Language :: Python
Classifier: Programming Language :: Python :: 2.7
Classifier: Programming Language :: Python :: 3.2
Classifier: Development Status :: 5 - Production/Stable
Classifier: License :: OSI Approved :: GNU Lesser General Public License v3 (LGPLv3)
Classifier: Operating System :: OS Independent
Classifier: Topic :: Software Development :: Libraries :: Python Modules
Classifier: Topic :: Text Processing :: General
